{
  "profile": {
    "favorite": [
      "đọc sách",
      "lập trình",
      "Ai",
      "AI",
      "làm bác sỹ",
      "làm thẩm mỹ",
      "làm đẹp",
      "nghiên cứu",
      "mổ xẻ bệnh nhân",
      "thẩm mỹ"
    ],
    "age": "35",
    "name": "Huy"
  },
  "history": [
    "👤 Bạn biết gì về tôi",
    "🤖 👤 Tên: gì<br>🎂 Tuổi: 35<br>❤️ Sở thích:<br>• đọc sách<br>• lập trình<br>• Ai<br>• AI<br>• làm bác sỹ<br>• làm thẩm mỹ<br>• làm đẹp<br>• nghiên cứu<br>• mổ xẻ bệnh nhân<br>• thẩm mỹ",
    "👤 Chào",
    "🤖 Xin chào 👋",
    "👤 Tên tôi là Huy",
    "🤖 Mình sẽ nhớ bạn tên là Huy 😊",
    "👤 Tên tôi là gì",
    "🤖 Bạn tên là Huy 😊",
    "👤 Bầu trời có màu xanh vì sao",
    "🤖 Bầu trời có màu xanh do hiện tượng tán xạ Rayleigh.",
    "👤 Nhiệt độ sôi bao nhiêu",
    "🤖 Thủ đô của Việt Nam là Hà Nội.",
    "👤 Tên tôi là gì",
    "🤖 Bạn tên là Huy 😊",
    "👤 Nhiệt độ sôi của nước là bao nhiêu",
    "🤖 Ở áp suất khí quyển tiêu chuẩn, nước sôi ở khoảng 100°C.",
    "👤 Bầu trời có màu xanh vì sao",
    "🤖 Bầu trời có màu xanh do hiện tượng tán xạ Rayleigh.",
    "👤 Bạn biết gì về tôi",
    "🤖 👤 Tên: Huy<br>🎂 Tuổi: 35<br>❤️ Sở thích:<br>• đọc sách<br>• lập trình<br>• Ai<br>• AI<br>• làm bác sỹ<br>• làm thẩm mỹ<br>• làm đẹp<br>• nghiên cứu<br>• mổ xẻ bệnh nhân<br>• thẩm mỹ",
    "👤 Nhiệt độ sôi của nước bao nhiêu",
    "🤖 Ở áp suất khí quyển tiêu chuẩn, nước sôi ở khoảng 100°C.",
    "👤 Chào",
    "🤖 Xin chào 👋",
    "👤 Tôi tên là Huy",
    "🤖 Mình sẽ nhớ bạn tên là Huy 😊",
    "👤 Tôi 35 tuổi",
    "🤖 ⚠️ Gemini API Key không hợp lệ.",
    "👤 Tôi ở Hà Nội",
    "🤖 Thủ đô của Việt Nam là Hà Nội.",
    "👤 Tôi thích AI",
    "🤖 Mình là AnOS AI Assistant.",
    "👤 Tên tôi là gì",
    "🤖 Mình sẽ nhớ bạn tên là gì 😊",
    "👤 Bạn biết gì về tôi",
    "🤖 👤 Tên: gì<br>🎂 Tuổi: 35<br>❤️ Sở thích:<br>• đọc sách<br>• lập trình<br>• Ai<br>• AI<br>• làm bác sỹ<br>• làm thẩm mỹ<br>• làm đẹp<br>• nghiên cứu<br>• mổ xẻ bệnh nhân<br>• thẩm mỹ",
    "👤 Chào",
    "🤖 Xin chào 👋",
    "👤 Tôi tên là Huy",
    "🤖 Mình sẽ nhớ bạn tên là Huy 😊",
    "👤 Tôi tên gì",
    "🤖 Bạn tên là Huy 😊",
    "👤 Bạn biết gì về tôi",
    "🤖 👤 Tên: Huy<br>🎂 Tuổi: 35<br>❤️ Sở thích:<br>• đọc sách<br>• lập trình<br>• Ai<br>• AI<br>• làm bác sỹ<br>• làm thẩm mỹ<br>• làm đẹp<br>• nghiên cứu<br>• mổ xẻ bệnh nhân<br>• thẩm mỹ",
    "👤 Bầu trời có màu xanh vì sao",
    "🤖 Bầu trời có màu xanh do hiện tượng tán xạ Rayleigh.",
    "👤 Nhiệt độ sôi của nước là bao nhiêu",
    "🤖 Ở áp suất khí quyển tiêu chuẩn, nước sôi ở khoảng 100°C.",
    "👤 Quên tên",
    "🤖 Mình đã quên tên của bạn. 😊",
    "👤 Tôi tên là gì",
    "🤖 Mình sẽ nhớ bạn tên là gì 😊",
    "👤 Mình tên là Huy",
    "🤖 Mình là AnOS AI Assistant.",
    "👤 Tôi tên là Huy",
    "🤖 Mình sẽ nhớ bạn tên là Huy 😊",
    "👤 Tôi tên là gì",
    "🤖 Mình sẽ nhớ bạn tên là gì 😊",
    "👤 Quên tên",
    "🤖 Mình đã quên tên của bạn. 😊",
    "👤 Tôi tên là Huy",
    "🤖 Mình sẽ nhớ bạn tên là Huy 😊",
    "👤 Tôi tên gì",
    "🤖 Bạn tên là Huy 😊",
    "👤 Chào",
    "🤖 Xin chào 👋",
    "👤 Chào",
    "🤖 Xin chào 👋",
    "👤 Hãy phân tích về tôi",
    "🤖 ⚠️ Gemini API Key không hợp lệ.",
    "👤 Bạn biết gì về tôi",
    "🤖 👤 Tên: Huy<br>🎂 Tuổi: 35<br>❤️ Sở thích:<br>• đọc sách<br>• lập trình<br>• Ai<br>• AI<br>• làm bác sỹ<br>• làm thẩm mỹ<br>• làm đẹp<br>• nghiên cứu<br>• mổ xẻ bệnh nhân<br>• thẩm mỹ",
    "👤 Tôi tên gì",
    "🤖 Bạn tên là Huy 😊",
    "👤 Phân tích tôi",
    "🤖 ⚠️ Gemini API Key không hợp lệ.",
    "👤 Chào",
    "🤖 Xin chào 👋",
    "👤 Tôi tên là Huy",
    "🤖 Mình sẽ nhớ bạn tên là Huy 😊",
    "👤 Tôi thích lập trình",
    "🤖 Mình sẽ nhớ bạn thích lập trình 😊",
    "👤 Bạn biết gì về tôi",
    "🤖 👤 Tên: Huy<br>🎂 Tuổi: 35<br>❤️ Sở thích:<br>• đọc sách<br>• lập trình<br>• Ai<br>• AI<br>• làm bác sỹ<br>• làm thẩm mỹ<br>• làm đẹp<br>• nghiên cứu<br>• mổ xẻ bệnh nhân<br>• thẩm mỹ",
    "👤 Phân tích về tôi",
    "🤖 Tên của bạn là Huy. Bạn đang ở giai đoạn phát triển mạnh sự nghiệp.",
    "👤 Chào",
    "🤖 Xin chào 👋",
    "👤 Bạn biết gì về tôi",
    "🤖 👤 Tên: Huy<br>🎂 Tuổi: 35<br>❤️ Sở thích:<br>• đọc sách<br>• lập trình<br>• Ai<br>• AI<br>• làm bác sỹ<br>• làm thẩm mỹ<br>• làm đẹp<br>• nghiên cứu<br>• mổ xẻ bệnh nhân<br>• thẩm mỹ",
    "👤 Phân tích về tôi",
    "🤖 Tên của bạn là Huy. Bạn đang ở giai đoạn phát triển mạnh sự nghiệp.",
    "👤 Chào",
    "🤖 Xin chào 👋",
    "👤 Phân tích về tôi",
    "🤖 Tên của bạn là Huy. Bạn đang ở giai đoạn phát triển mạnh sự nghiệp.",
    "👤 Hãy phân tích tôi",
    "🤖 Tên của bạn là Huy. Bạn đang ở giai đoạn phát triển mạnh sự nghiệp. Bạn thích đọc sách, lập trình, Ai, AI, làm bác sỹ, làm thẩm mỹ, làm đẹp, nghiên cứu, mổ xẻ bệnh nhân, thẩm mỹ. Bạn có xu hướng yêu thích công nghệ. Bạn rất quan tâm đến trí tuệ nhân tạo. Bạn có tinh thần học hỏi. Bạn thích tìm tòi và khám phá kiến thức mới. Bạn quan tâm đến lĩnh vực y khoa và chăm sóc sức khỏe. Bạn cũng có hứng thú với lĩnh vực thẩm mỹ và làm đẹp.",
    "👤 Hãy phân tích tôi",
    "🤖 Tên của bạn là Huy. Bạn đang ở giai đoạn phát triển mạnh sự nghiệp. Bạn thích đọc sách, lập trình, ai, làm bác sỹ, làm thẩm mỹ, làm đẹp, nghiên cứu, mổ xẻ bệnh nhân, thẩm mỹ. Bạn có xu hướng yêu thích công nghệ. Bạn rất quan tâm đến trí tuệ nhân tạo. Bạn có tinh thần học hỏi. Bạn thích tìm tòi và khám phá kiến thức mới. Bạn quan tâm đến lĩnh vực y khoa và chăm sóc sức khỏe. Bạn cũng có hứng thú với lĩnh vực thẩm mỹ và làm đẹp. Có thể bạn đang hướng tới việc phát triển hoặc nghiên cứu các ứng dụng AI. Bạn là người thích tự học và khám phá kiến thức mới. Bạn quan tâm đến cả y khoa và thẩm mỹ, có xu hướng kết hợp kiến thức chuyên môn với tính ứng dụng. Bạn có xu hướng tìm hiểu AI ở mức chuyên sâu thay vì chỉ sử dụng. Đây là phân tích dựa trên những thông tin mình đang lưu. Khi có thêm dữ liệu về bạn, mình sẽ đưa ra những nhận xét chính xác và chi tiết hơn."
  ],
  "tasks": [
    {
      "id": 1783901411567,
      "title": "Mua sữa",
      "done": false,
      "created": "2026-07-13T00:10:11.567Z"
    }
  ]
}